{"kind": "youtube#video", "etag": "998W68exRNIPkM658at2OZYfYfo", "id": "-wnzqOWSdhU", "snippet": {"publishedAt": "2019-03-25T06:08:11Z", "channelId": "UC1fLEeYICmo3O9cUsqIi7HA", "title": "HackerRank Find Merge Point Of Two Lists Solution Explained - Java", "description": "Facebook - https://www.facebook.com/NicholasWhit...\nPatreon - https://www.patreon.com/nick_white?al...\nTwitch - https://www.twitch.tv/matrixman\nReddit - https://www.reddit.com/r/NickWhiteCod...\nTwitter - https://twitter.com/nickdoubleyouu\nInstagram - https://instagram.com/nickdoubleyou\nLinkedin - https://www.linkedin.com/in/nicholas-...\nGithub - https://github.com/white105\nDiscord - https://discordapp.com/invite/vQH4vSJ\nSoundcloud - https://soundcloud.com/nickiswhite", "thumbnails": {"default": {"url": "https://i.ytimg.com/vi/-wnzqOWSdhU/default.jpg", "width": 120, "height": 90}, "medium": {"url": "https://i.ytimg.com/vi/-wnzqOWSdhU/mqdefault.jpg", "width": 320, "height": 180}, "high": {"url": "https://i.ytimg.com/vi/-wnzqOWSdhU/hqdefault.jpg", "width": 480, "height": 360}, "standard": {"url": "https://i.ytimg.com/vi/-wnzqOWSdhU/sddefault.jpg", "width": 640, "height": 480}, "maxres": {"url": "https://i.ytimg.com/vi/-wnzqOWSdhU/maxresdefault.jpg", "width": 1280, "height": 720}}, "channelTitle": "Nick White", "tags": ["leetcode", "hackerrank", "cracking the coding interview", "coding", "programming", "computer", "computer science", "technology", "tech", "technical interview", "math", "science", "coding questions", "java", "python", "list", "lists", "linked lists", "find merge point of two lists", "linked list", "merging", "searching", "comparison", "sorting", "merge", "how to", "tutorial", "explained", "solution", "education", "algorithms", "data structures", "whiteboarding", "codepen"], "categoryId": "28", "liveBroadcastContent": "none", "localized": {"title": "HackerRank Find Merge Point Of Two Lists Solution Explained - Java", "description": "Facebook - https://www.facebook.com/NicholasWhit...\nPatreon - https://www.patreon.com/nick_white?al...\nTwitch - https://www.twitch.tv/matrixman\nReddit - https://www.reddit.com/r/NickWhiteCod...\nTwitter - https://twitter.com/nickdoubleyouu\nInstagram - https://instagram.com/nickdoubleyou\nLinkedin - https://www.linkedin.com/in/nicholas-...\nGithub - https://github.com/white105\nDiscord - https://discordapp.com/invite/vQH4vSJ\nSoundcloud - https://soundcloud.com/nickiswhite"}}, "contentDetails": {"duration": "PT9M6S", "dimension": "2d", "definition": "hd", "caption": "false", "licensedContent": true, "contentRating": {}, "projection": "rectangular"}, "statistics": {"viewCount": "2349", "likeCount": "52", "dislikeCount": "1", "favoriteCount": "0", "commentCount": "13"}, "topicDetails": {"relevantTopicIds": ["/m/01k8wb", "/m/01k8wb"], "topicCategories": ["https://en.wikipedia.org/wiki/Knowledge"]}, "has_face": false, "detection_confidence": null}