{"kind": "youtube#video", "etag": "KssS8lVc7UxVv1VBRokGT2gLW1o", "id": "3Bf2Y9NBcck", "snippet": {"publishedAt": "2019-01-03T20:00:01Z", "channelId": "UC_fFL5jgoCOrwAVoM_fBYwA", "title": "Java Int Variables", "description": "New course coming soon! Learn Java Fast launches on July 1st, 2020. Stay informed and join the waitlist: https://course.alexlorenlee.com/courses/learn-java-fast\n\n- In this video, I walk you through exactly how to create integer variables in java! \u2705I also teach you some facts you may not have known about the java int variable! \n\n\ud83d\udc51Start practicing now with 10 free java programs - http://alexlorenlee.com/\n\ud83c\udf05 Source Code - https://github.com/alexlorenlee/JavaTutorialCode/blob/master/Numbers/Integers.java\n\nAll you need to do is this: int a = 2. This will store 2 into the letter a. So anytime we use a, say in a print statement or for doing math, it will use the value 2. \n\nThe java int variable can be tricky... But once you practice integers in java you'll surely get the hang of them! Java integers aren't too bad :) If you followed along, congrats! You learned-by-doing!\n\nI hope you enjoyed this tutorial on how to use integer variables in java! I like to have a nice mix of tutorials and actual projects for you all :)\n\nDo you want to learn how to code from scratch, in Java? Check out my Java Tutorial For Beginners: https://youtu.be/woJb2hAfkO0\n\nHow are you using integer variables? -\n\nFree tips and programs: http://alexlorenlee.com\n\nRecommended Channels to Subscribe to\nCareer Karma: https://youtube.com/channel/UCkCwv67-...\nTheNewBoston: https://youtube.com/user/thenewboston\n\n~\nhttps://discord.com/invite/Yk3uqST\nhttps://instagram.com/alexlorenlee\nhttps://youtube.com/channel/UCLkeDGcXfiKlN2imazwkg4A (2nd channel)\n\nAlex Lee", "thumbnails": {"default": {"url": "https://i.ytimg.com/vi/3Bf2Y9NBcck/default.jpg", "width": 120, "height": 90}, "medium": {"url": "https://i.ytimg.com/vi/3Bf2Y9NBcck/mqdefault.jpg", "width": 320, "height": 180}, "high": {"url": "https://i.ytimg.com/vi/3Bf2Y9NBcck/hqdefault.jpg", "width": 480, "height": 360}, "standard": {"url": "https://i.ytimg.com/vi/3Bf2Y9NBcck/sddefault.jpg", "width": 640, "height": 480}, "maxres": {"url": "https://i.ytimg.com/vi/3Bf2Y9NBcck/maxresdefault.jpg", "width": 1280, "height": 720}}, "channelTitle": "Alex Lee", "tags": ["java int variable", "java int variables", "integer variables in java", "integer variables", "how to use integers java", "java int", "java integer tutorial", "int in java", "ints in java", "int java", "use integers in java", "how to use integers in java", "integers in java", "java integer", "java variables", "integer in java", "basic java", "java integers", "integer", "integers", "int", "ints", "java ints", "learn java"], "categoryId": "27", "liveBroadcastContent": "none", "localized": {"title": "Java Int Variables", "description": "New course coming soon! Learn Java Fast launches on July 1st, 2020. Stay informed and join the waitlist: https://course.alexlorenlee.com/courses/learn-java-fast\n\n- In this video, I walk you through exactly how to create integer variables in java! \u2705I also teach you some facts you may not have known about the java int variable! \n\n\ud83d\udc51Start practicing now with 10 free java programs - http://alexlorenlee.com/\n\ud83c\udf05 Source Code - https://github.com/alexlorenlee/JavaTutorialCode/blob/master/Numbers/Integers.java\n\nAll you need to do is this: int a = 2. This will store 2 into the letter a. So anytime we use a, say in a print statement or for doing math, it will use the value 2. \n\nThe java int variable can be tricky... But once you practice integers in java you'll surely get the hang of them! Java integers aren't too bad :) If you followed along, congrats! You learned-by-doing!\n\nI hope you enjoyed this tutorial on how to use integer variables in java! I like to have a nice mix of tutorials and actual projects for you all :)\n\nDo you want to learn how to code from scratch, in Java? Check out my Java Tutorial For Beginners: https://youtu.be/woJb2hAfkO0\n\nHow are you using integer variables? -\n\nFree tips and programs: http://alexlorenlee.com\n\nRecommended Channels to Subscribe to\nCareer Karma: https://youtube.com/channel/UCkCwv67-...\nTheNewBoston: https://youtube.com/user/thenewboston\n\n~\nhttps://discord.com/invite/Yk3uqST\nhttps://instagram.com/alexlorenlee\nhttps://youtube.com/channel/UCLkeDGcXfiKlN2imazwkg4A (2nd channel)\n\nAlex Lee"}, "defaultAudioLanguage": "en"}, "contentDetails": {"duration": "PT5M10S", "dimension": "2d", "definition": "hd", "caption": "false", "licensedContent": true, "contentRating": {}, "projection": "rectangular"}, "statistics": {"viewCount": "12223", "likeCount": "505", "dislikeCount": "3", "favoriteCount": "0", "commentCount": "20"}, "topicDetails": {"relevantTopicIds": ["/m/01k8wb", "/m/01k8wb"], "topicCategories": ["https://en.wikipedia.org/wiki/Knowledge"]}, "has_face": true, "detection_confidence": 0.9992328882217407}