{"kind": "youtube#video", "etag": "PIjyloQSDtP5BfA2obwRd14LcwU", "id": "514A7yzznJE", "snippet": {"publishedAt": "2020-01-02T15:00:01Z", "channelId": "UCuP2vJ6kRutQBfRmdcI92mA", "title": "SwiftUI Fullscreen Modal Hack withAnimation", "description": "Something missing in SwiftUI right now is the ability to present a modal fullscreen. With a little bit of creativity we can hack in a solution that animates a view to the top of our device very easily. Laying out these components is quite easy with the SwiftUI framework so we'll learn exactly the implementation in this lesson.\n\nMaps UIKit SwiftUI\nhttps://www.letsbuildthatapp.com/course/Maps-UIKit-SwiftUI\n\nFullstack Social NodeJS iOS HTML:\nhttps://www.letsbuildthatapp.com/course/Fullstack-Social-iOS-NodeJS-REST\n\nAppStore JSON APIs\nhttps://www.letsbuildthatapp.com/course/AppStore-JSON-APIs\n\nTinder Firestore Swipe and Match\nhttps://www.letsbuildthatapp.com/course/Tinder-Firestore-Swipe-and-Match\n\nTwitter Slide Out Menu Course\nhttps://www.letsbuildthatapp.com/course/Twitter-Slide-Out-Menu\n\nPodcasts Course\nhttps://www.letsbuildthatapp.com/course/Podcasts\n\nIntermediate Training Core Data\nhttps://www.letsbuildthatapp.com/course/intermediate-training-core-data\n\nFacebook Group\nhttps://www.facebook.com/groups/1240636442694543/\n\nCompleted Source Code\nhttps://www.letsbuildthatapp.com/course_video?id=6252\n\nInstagram: https://www.instagram.com/buildthatapp/\nTwitter: https://twitter.com/buildthatapp", "thumbnails": {"default": {"url": "https://i.ytimg.com/vi/514A7yzznJE/default.jpg", "width": 120, "height": 90}, "medium": {"url": "https://i.ytimg.com/vi/514A7yzznJE/mqdefault.jpg", "width": 320, "height": 180}, "high": {"url": "https://i.ytimg.com/vi/514A7yzznJE/hqdefault.jpg", "width": 480, "height": 360}, "standard": {"url": "https://i.ytimg.com/vi/514A7yzznJE/sddefault.jpg", "width": 640, "height": 480}, "maxres": {"url": "https://i.ytimg.com/vi/514A7yzznJE/maxresdefault.jpg", "width": 1280, "height": 720}}, "channelTitle": "Lets Build That App", "tags": ["ios", "swift", "development", "tutorial", "learn", "xcode", "programming", "code"], "categoryId": "27", "liveBroadcastContent": "none", "defaultLanguage": "en", "localized": {"title": "SwiftUI Fullscreen Modal Hack withAnimation", "description": "Something missing in SwiftUI right now is the ability to present a modal fullscreen. With a little bit of creativity we can hack in a solution that animates a view to the top of our device very easily. Laying out these components is quite easy with the SwiftUI framework so we'll learn exactly the implementation in this lesson.\n\nMaps UIKit SwiftUI\nhttps://www.letsbuildthatapp.com/course/Maps-UIKit-SwiftUI\n\nFullstack Social NodeJS iOS HTML:\nhttps://www.letsbuildthatapp.com/course/Fullstack-Social-iOS-NodeJS-REST\n\nAppStore JSON APIs\nhttps://www.letsbuildthatapp.com/course/AppStore-JSON-APIs\n\nTinder Firestore Swipe and Match\nhttps://www.letsbuildthatapp.com/course/Tinder-Firestore-Swipe-and-Match\n\nTwitter Slide Out Menu Course\nhttps://www.letsbuildthatapp.com/course/Twitter-Slide-Out-Menu\n\nPodcasts Course\nhttps://www.letsbuildthatapp.com/course/Podcasts\n\nIntermediate Training Core Data\nhttps://www.letsbuildthatapp.com/course/intermediate-training-core-data\n\nFacebook Group\nhttps://www.facebook.com/groups/1240636442694543/\n\nCompleted Source Code\nhttps://www.letsbuildthatapp.com/course_video?id=6252\n\nInstagram: https://www.instagram.com/buildthatapp/\nTwitter: https://twitter.com/buildthatapp"}, "defaultAudioLanguage": "en"}, "contentDetails": {"duration": "PT14M14S", "dimension": "2d", "definition": "hd", "caption": "false", "licensedContent": true, "contentRating": {}, "projection": "rectangular"}, "statistics": {"viewCount": "13789", "likeCount": "363", "dislikeCount": "13", "favoriteCount": "0", "commentCount": "53"}, "topicDetails": {"relevantTopicIds": ["/m/01k8wb", "/m/01k8wb"], "topicCategories": ["https://en.wikipedia.org/wiki/Knowledge"]}, "has_face": true, "detection_confidence": 0.9999954700469971}