{"kind": "youtube#video", "etag": "QIhso7UL6K034JkNeSpEKO_OyOM", "id": "7-sxw0cD0UU", "snippet": {"publishedAt": "2016-12-04T04:31:38Z", "channelId": "UCgkG68BiCngkoV7I2BLtAVg", "title": "Python Tutorial - Starting Your Cookbook", "description": "Learn how to start a Python cookbook using PyCharm, Git, and GitHub. This tutorial will walk through creating a repository, cloning it, writing our first program, running it, commiting and pushing it up to GitHub. Learn how to use the PyCharm IDE as well as program with Python while building up your own repository of programs. This is perfect for beginners.\n\nImportant Links:\n\n* DevDungeon - Starting your Python Tutorial - http://www.devdungeon.com/content/python-tutorial-starting-your-cookbook\n* Python - http://www.python.org/download\n* PyCharm - http://www.jetbrains.com/pycharm\n* GitHub - https://github.com\n* Git for Windows - https://git-scm.com/download/win\n* The Cookbook Method - http://www.devdungeon.com/cookbook", "thumbnails": {"default": {"url": "https://i.ytimg.com/vi/7-sxw0cD0UU/default.jpg", "width": 120, "height": 90}, "medium": {"url": "https://i.ytimg.com/vi/7-sxw0cD0UU/mqdefault.jpg", "width": 320, "height": 180}, "high": {"url": "https://i.ytimg.com/vi/7-sxw0cD0UU/hqdefault.jpg", "width": 480, "height": 360}, "standard": {"url": "https://i.ytimg.com/vi/7-sxw0cD0UU/sddefault.jpg", "width": 640, "height": 480}, "maxres": {"url": "https://i.ytimg.com/vi/7-sxw0cD0UU/maxresdefault.jpg", "width": 1280, "height": 720}}, "channelTitle": "DevDungeon", "tags": ["Learn Programming", "Programming", "Software Development", "Learn Coding", "Beginner Python", "Python Tutorial", "Hello world", "Python Hello World", "Python Programming", "Programming Tutorial", "Beginner", "Introduction Python"], "categoryId": "28", "liveBroadcastContent": "none", "defaultLanguage": "en", "localized": {"title": "Python Tutorial - Starting Your Cookbook", "description": "Learn how to start a Python cookbook using PyCharm, Git, and GitHub. This tutorial will walk through creating a repository, cloning it, writing our first program, running it, commiting and pushing it up to GitHub. Learn how to use the PyCharm IDE as well as program with Python while building up your own repository of programs. This is perfect for beginners.\n\nImportant Links:\n\n* DevDungeon - Starting your Python Tutorial - http://www.devdungeon.com/content/python-tutorial-starting-your-cookbook\n* Python - http://www.python.org/download\n* PyCharm - http://www.jetbrains.com/pycharm\n* GitHub - https://github.com\n* Git for Windows - https://git-scm.com/download/win\n* The Cookbook Method - http://www.devdungeon.com/cookbook"}, "defaultAudioLanguage": "en"}, "contentDetails": {"duration": "PT9M14S", "dimension": "2d", "definition": "hd", "caption": "true", "licensedContent": true, "contentRating": {}, "projection": "rectangular"}, "statistics": {"viewCount": "2641", "likeCount": "57", "dislikeCount": "2", "favoriteCount": "0", "commentCount": "5"}, "topicDetails": {"relevantTopicIds": ["/m/01k8wb", "/m/01k8wb"], "topicCategories": ["https://en.wikipedia.org/wiki/Knowledge"]}, "has_face": false, "detection_confidence": null}