{"kind": "youtube#video", "etag": "Y1CEiTFEwFj44BKOweQDhOeKVG0", "id": "bt6QQORL110", "snippet": {"publishedAt": "2019-03-02T16:10:28Z", "channelId": "UCWr0mx597DnSGLFk1WfvSkQ", "title": "How To Get 8 Hours of Work Done in 1 Hour", "description": "How To Get 8 Hours of Work Done in 1 Hour\n\nJust a few tips that have helped me improve my time management and increase my productivity.\n\nCONTACT: halldenkalle@gmail.com\n\nComputer: Macbook Pro - https://amzn.to/2GX54SU\n\n\nCamera Gear:\n\nPanasonic GH5 - https://amzn.to/2Nr09L2\n\nMAIN LENS:  Lumix 12-35mm - https://amzn.to/2tzgJzp\n\nDRONE: DJI Mavic Air - https://amzn.to/2NqkQa1\n\nSecondary Lens: Panasonic 25mm - https://amzn.to/2UcTA1e\n\nSecondary Lens: Olympus 45mm - https://amzn.to/2Ebp5SV\n\nZoom Lens: Panasonic 100-300mm - https://amzn.to/2U3UH3j\n\nMonitor: AOC 27\u201d - https://amzn.to/2U6hF9Z", "thumbnails": {"default": {"url": "https://i.ytimg.com/vi/bt6QQORL110/default.jpg", "width": 120, "height": 90}, "medium": {"url": "https://i.ytimg.com/vi/bt6QQORL110/mqdefault.jpg", "width": 320, "height": 180}, "high": {"url": "https://i.ytimg.com/vi/bt6QQORL110/hqdefault.jpg", "width": 480, "height": 360}, "standard": {"url": "https://i.ytimg.com/vi/bt6QQORL110/sddefault.jpg", "width": 640, "height": 480}, "maxres": {"url": "https://i.ytimg.com/vi/bt6QQORL110/maxresdefault.jpg", "width": 1280, "height": 720}}, "channelTitle": "Kalle Hallden", "tags": ["time management strategies", "how to improve productivity", "how to improve my productivity", "time management tips for students", "How To Get 8 Hours of Work Done in 1 Hour", "how to manage time for study", "time management tips", "how to manage time effectively", "how to manage time in college", "time management tips for entrepreneurs", "how to get more done", "how to get more done in less time", "productivity tips", "how to improve your productivity", "how to improve productivity in school"], "categoryId": "22", "liveBroadcastContent": "none", "localized": {"title": "How To Get 8 Hours of Work Done in 1 Hour", "description": "How To Get 8 Hours of Work Done in 1 Hour\n\nJust a few tips that have helped me improve my time management and increase my productivity.\n\nCONTACT: halldenkalle@gmail.com\n\nComputer: Macbook Pro - https://amzn.to/2GX54SU\n\n\nCamera Gear:\n\nPanasonic GH5 - https://amzn.to/2Nr09L2\n\nMAIN LENS:  Lumix 12-35mm - https://amzn.to/2tzgJzp\n\nDRONE: DJI Mavic Air - https://amzn.to/2NqkQa1\n\nSecondary Lens: Panasonic 25mm - https://amzn.to/2UcTA1e\n\nSecondary Lens: Olympus 45mm - https://amzn.to/2Ebp5SV\n\nZoom Lens: Panasonic 100-300mm - https://amzn.to/2U3UH3j\n\nMonitor: AOC 27\u201d - https://amzn.to/2U6hF9Z"}}, "contentDetails": {"duration": "PT7M40S", "dimension": "2d", "definition": "hd", "caption": "false", "licensedContent": true, "contentRating": {}, "projection": "rectangular"}, "statistics": {"viewCount": "29255", "likeCount": "1160", "dislikeCount": "12", "favoriteCount": "0", "commentCount": "78"}, "has_face": true, "detection_confidence": 0.9999872446060181}