{"kind": "youtube#video", "etag": "hkBvf_OnAoYzKZN3AnXSXa8B478", "id": "H0LNjF9PSeM", "snippet": {"publishedAt": "2020-05-07T19:00:08Z", "channelId": "UC_fFL5jgoCOrwAVoM_fBYwA", "title": "Java Type Casting Tutorial", "description": "New course coming soon! Learn Java Fast launches on July 1st, 2020. Stay informed and join the waitlist: https://course.alexlorenlee.com/courses/learn-java-fast\n\n- This is how you cast a variable in java. \u2615\n\nint a = (int) b;\n\nSimply put the type you want it to be in parentheses. That's it! Java will now cast your variable to be the variable type you want.\n\nI hope this helps you with java type casting! This is great practice :)\n\nI hope you enjoyed java type casting tutorial!\n\n------------------------------------------------------------------------------------------ -\n\nFree tips and programs: http://alexlorenlee.com\n\nRecommended Channels to Subscribe to\nCareer Karma: https://youtube.com/channel/UCkCwv67-HTCzIhxLG8aHOQQ\nTheNewBoston: https://youtube.com/user/thenewboston\n\n~\nhttps://discord.com/invite/Yk3uqST\nhttps://instagram.com/alexlorenlee\nhttps://youtube.com/channel/UCLkeDGcXfiKlN2imazwkg4A (2nd channel)\n\nAlex Lee", "thumbnails": {"default": {"url": "https://i.ytimg.com/vi/H0LNjF9PSeM/default.jpg", "width": 120, "height": 90}, "medium": {"url": "https://i.ytimg.com/vi/H0LNjF9PSeM/mqdefault.jpg", "width": 320, "height": 180}, "high": {"url": "https://i.ytimg.com/vi/H0LNjF9PSeM/hqdefault.jpg", "width": 480, "height": 360}, "standard": {"url": "https://i.ytimg.com/vi/H0LNjF9PSeM/sddefault.jpg", "width": 640, "height": 480}, "maxres": {"url": "https://i.ytimg.com/vi/H0LNjF9PSeM/maxresdefault.jpg", "width": 1280, "height": 720}}, "channelTitle": "Alex Lee", "tags": ["java type casting", "java type casting tutorial", "java typecasting", "typecasting java", "type casting java", "type cast java", "type cast java tutorial", "type casting in java", "java", "java tutorial", "java cast type", "cast type java", "cast type in java", "alex lee"], "categoryId": "27", "liveBroadcastContent": "none", "localized": {"title": "Java Type Casting Tutorial", "description": "New course coming soon! Learn Java Fast launches on July 1st, 2020. Stay informed and join the waitlist: https://course.alexlorenlee.com/courses/learn-java-fast\n\n- This is how you cast a variable in java. \u2615\n\nint a = (int) b;\n\nSimply put the type you want it to be in parentheses. That's it! Java will now cast your variable to be the variable type you want.\n\nI hope this helps you with java type casting! This is great practice :)\n\nI hope you enjoyed java type casting tutorial!\n\n------------------------------------------------------------------------------------------ -\n\nFree tips and programs: http://alexlorenlee.com\n\nRecommended Channels to Subscribe to\nCareer Karma: https://youtube.com/channel/UCkCwv67-HTCzIhxLG8aHOQQ\nTheNewBoston: https://youtube.com/user/thenewboston\n\n~\nhttps://discord.com/invite/Yk3uqST\nhttps://instagram.com/alexlorenlee\nhttps://youtube.com/channel/UCLkeDGcXfiKlN2imazwkg4A (2nd channel)\n\nAlex Lee"}, "defaultAudioLanguage": "en"}, "contentDetails": {"duration": "PT5M50S", "dimension": "2d", "definition": "hd", "caption": "false", "licensedContent": true, "contentRating": {}, "projection": "rectangular"}, "statistics": {"viewCount": "6094", "likeCount": "375", "dislikeCount": "1", "favoriteCount": "0", "commentCount": "65"}, "topicDetails": {"relevantTopicIds": ["/m/01k8wb", "/m/01k8wb"], "topicCategories": ["https://en.wikipedia.org/wiki/Knowledge"]}, "has_face": true, "detection_confidence": 0.9999167919158936}