{"kind": "youtube#video", "etag": "MGNfeHQHys3sYHfRARS_Bzb70bs", "id": "IHT8Sx0832k", "snippet": {"publishedAt": "2019-09-12T03:21:49Z", "channelId": "UC1fLEeYICmo3O9cUsqIi7HA", "title": "LeetCode Open the Lock Solution Explained - Java", "description": "Patreon - https://www.patreon.com/nick_white?al...\n\nProblem URL - https://leetcode.com/problems/open-the-lock/\n\n___\nFacebook - https://www.facebook.com/NicholasWhit...\nTwitch - https://www.twitch.tv/matrixman\nReddit - https://www.reddit.com/r/NickWhiteCod...\nTwitter - https://twitter.com/nicholaswwhite\nInstagram - https://instagram.com/nickwwhite\nhttps://www.linkedin.com/in/nicholas-...\nGithub - https://github.com/white105\nDiscord - https://discordapp.com/invite/vQH4vSJ\nSoundcloud - https://soundcloud.com/nickiswhite", "thumbnails": {"default": {"url": "https://i.ytimg.com/vi/IHT8Sx0832k/default.jpg", "width": 120, "height": 90}, "medium": {"url": "https://i.ytimg.com/vi/IHT8Sx0832k/mqdefault.jpg", "width": 320, "height": 180}, "high": {"url": "https://i.ytimg.com/vi/IHT8Sx0832k/hqdefault.jpg", "width": 480, "height": 360}, "standard": {"url": "https://i.ytimg.com/vi/IHT8Sx0832k/sddefault.jpg", "width": 640, "height": 480}, "maxres": {"url": "https://i.ytimg.com/vi/IHT8Sx0832k/maxresdefault.jpg", "width": 1280, "height": 720}}, "channelTitle": "Nick White", "tags": ["leetcode", "hacker rank", "cracking the coding interview", "coding", "programming", "computer science", "technology", "math", "science", "education", "tutorial", "how to", "python", "java", "web development", "software engineering", "algorithms", "data structures", "interview", "technical interview", "coding questions"], "categoryId": "28", "liveBroadcastContent": "none", "localized": {"title": "LeetCode Open the Lock Solution Explained - Java", "description": "Patreon - https://www.patreon.com/nick_white?al...\n\nProblem URL - https://leetcode.com/problems/open-the-lock/\n\n___\nFacebook - https://www.facebook.com/NicholasWhit...\nTwitch - https://www.twitch.tv/matrixman\nReddit - https://www.reddit.com/r/NickWhiteCod...\nTwitter - https://twitter.com/nicholaswwhite\nInstagram - https://instagram.com/nickwwhite\nhttps://www.linkedin.com/in/nicholas-...\nGithub - https://github.com/white105\nDiscord - https://discordapp.com/invite/vQH4vSJ\nSoundcloud - https://soundcloud.com/nickiswhite"}}, "contentDetails": {"duration": "PT15M36S", "dimension": "2d", "definition": "hd", "caption": "false", "licensedContent": true, "contentRating": {}, "projection": "rectangular"}, "statistics": {"viewCount": "3755", "likeCount": "106", "dislikeCount": "1", "favoriteCount": "0", "commentCount": "15"}, "topicDetails": {"relevantTopicIds": ["/m/01k8wb", "/m/01k8wb"], "topicCategories": ["https://en.wikipedia.org/wiki/Knowledge"]}, "has_face": true, "detection_confidence": 0.9999997615814209}