{"kind": "youtube#video", "etag": "X-4HUMtwVWRQOZ07o1ZKro3FgCo", "id": "P5opi9tIuro", "snippet": {"publishedAt": "2018-08-30T14:00:01Z", "channelId": "UCuP2vJ6kRutQBfRmdcI92mA", "title": "Swift Grouped Messages: UITableView Section Date Headers (Ep 3)", "description": "In today's lesson, let's improve the look and feel of our application by providing some sections and headers. We'll be restructuring our messages to provide our table with the appropriate data. Finally, we can create a custom Date function that helps us create custom dates for our messages. Enjoy.\n\nPodcasts Course\nhttps://www.letsbuildthatapp.com/course/Podcasts\n\nIntermediate Training Core Data\nhttps://www.letsbuildthatapp.com/course/intermediate-training-core-data\n\nInstagram Firebase Course\nhttps://www.letsbuildthatapp.com/course/instagram-firebase\n\nFacebook Group\nhttps://www.facebook.com/groups/1240636442694543/\n\nCompleted Source Code\nhttps://www.letsbuildthatapp.com/course_video?id=3622\n\nInstagram: https://www.instagram.com/buildthatapp/\nTwitter: https://twitter.com/buildthatapp", "thumbnails": {"default": {"url": "https://i.ytimg.com/vi/P5opi9tIuro/default.jpg", "width": 120, "height": 90}, "medium": {"url": "https://i.ytimg.com/vi/P5opi9tIuro/mqdefault.jpg", "width": 320, "height": 180}, "high": {"url": "https://i.ytimg.com/vi/P5opi9tIuro/hqdefault.jpg", "width": 480, "height": 360}, "standard": {"url": "https://i.ytimg.com/vi/P5opi9tIuro/sddefault.jpg", "width": 640, "height": 480}, "maxres": {"url": "https://i.ytimg.com/vi/P5opi9tIuro/maxresdefault.jpg", "width": 1280, "height": 720}}, "channelTitle": "Lets Build That App", "tags": ["ios", "swift", "development", "tutorial", "learn", "xcode", "programming", "code"], "categoryId": "27", "liveBroadcastContent": "none", "defaultLanguage": "en", "localized": {"title": "Swift Grouped Messages: UITableView Section Date Headers (Ep 3)", "description": "In today's lesson, let's improve the look and feel of our application by providing some sections and headers. We'll be restructuring our messages to provide our table with the appropriate data. Finally, we can create a custom Date function that helps us create custom dates for our messages. Enjoy.\n\nPodcasts Course\nhttps://www.letsbuildthatapp.com/course/Podcasts\n\nIntermediate Training Core Data\nhttps://www.letsbuildthatapp.com/course/intermediate-training-core-data\n\nInstagram Firebase Course\nhttps://www.letsbuildthatapp.com/course/instagram-firebase\n\nFacebook Group\nhttps://www.facebook.com/groups/1240636442694543/\n\nCompleted Source Code\nhttps://www.letsbuildthatapp.com/course_video?id=3622\n\nInstagram: https://www.instagram.com/buildthatapp/\nTwitter: https://twitter.com/buildthatapp"}, "defaultAudioLanguage": "en"}, "contentDetails": {"duration": "PT18M55S", "dimension": "2d", "definition": "hd", "caption": "false", "licensedContent": true, "contentRating": {}, "projection": "rectangular"}, "statistics": {"viewCount": "15002", "likeCount": "308", "dislikeCount": "4", "favoriteCount": "0", "commentCount": "42"}, "topicDetails": {"relevantTopicIds": ["/m/01k8wb", "/m/01k8wb"], "topicCategories": ["https://en.wikipedia.org/wiki/Knowledge"]}, "has_face": true, "detection_confidence": 0.9999017715454102}