{"kind": "youtube#video", "etag": "N0IAuWjoIcIXjqlfL4rfvVD5x6g", "id": "QOHkSxwZ6MU", "snippet": {"publishedAt": "2020-04-10T20:42:02Z", "channelId": "UC1fLEeYICmo3O9cUsqIi7HA", "title": "I'm Sick (Probably Coronavirus)", "description": "Patreon - https://www.patreon.com/nick_white?al...\n\n___\nDiscord - https://discord.gg/2f2Tgy3\nTwitch - https://www.twitch.tv/matrixman\nTwitter - https://twitter.com/nicholaswwhite\nInstagram - https://instagram.com/nickwwhite\nLinkedIn - https://bit.ly/37AEo5j\nGithub - https://github.com/white105", "thumbnails": {"default": {"url": "https://i.ytimg.com/vi/QOHkSxwZ6MU/default.jpg", "width": 120, "height": 90}, "medium": {"url": "https://i.ytimg.com/vi/QOHkSxwZ6MU/mqdefault.jpg", "width": 320, "height": 180}, "high": {"url": "https://i.ytimg.com/vi/QOHkSxwZ6MU/hqdefault.jpg", "width": 480, "height": 360}, "standard": {"url": "https://i.ytimg.com/vi/QOHkSxwZ6MU/sddefault.jpg", "width": 640, "height": 480}, "maxres": {"url": "https://i.ytimg.com/vi/QOHkSxwZ6MU/maxresdefault.jpg", "width": 1280, "height": 720}}, "channelTitle": "Nick White", "tags": ["coding", "programming", "education", "tech", "swe", "software engineering", "software development", "software engineer", "software developer", "developer", "web developer", "coder", "programmer", "computer science", "computer programming", "code", "program", "sick", "health", "wellness", "im sick", "coronavirus", "covid-19", "asthma", "pnemonia", "hospital", "pandemic", "corona"], "categoryId": "28", "liveBroadcastContent": "none", "localized": {"title": "I'm Sick (Probably Coronavirus)", "description": "Patreon - https://www.patreon.com/nick_white?al...\n\n___\nDiscord - https://discord.gg/2f2Tgy3\nTwitch - https://www.twitch.tv/matrixman\nTwitter - https://twitter.com/nicholaswwhite\nInstagram - https://instagram.com/nickwwhite\nLinkedIn - https://bit.ly/37AEo5j\nGithub - https://github.com/white105"}}, "contentDetails": {"duration": "PT12M7S", "dimension": "2d", "definition": "hd", "caption": "false", "licensedContent": true, "contentRating": {}, "projection": "rectangular"}, "statistics": {"viewCount": "11759", "likeCount": "466", "dislikeCount": "34", "favoriteCount": "0", "commentCount": "283"}, "topicDetails": {"relevantTopicIds": ["/m/019_rr", "/m/0kt51", "/m/019_rr", "/m/0kt51"], "topicCategories": ["https://en.wikipedia.org/wiki/Health", "https://en.wikipedia.org/wiki/Lifestyle_(sociology)"]}, "has_face": true, "detection_confidence": 0.9991815686225891}