{"kind": "youtube#video", "etag": "xz8ByQdN3qv4LWI4TpqtuewOAnQ", "id": "S59b-XFsyY8", "snippet": {"publishedAt": "2018-04-30T14:30:00Z", "channelId": "UCuP2vJ6kRutQBfRmdcI92mA", "title": "Complete Guide to Flutter: How to Build a Real World App", "description": "Flutter hit the scene a few months back and has caught the attention of quite a few developers.  In this guide, we'll go through all the necessary aspects of building out a Real World app that includes many features such as Reactive States, Networking, JSON Decoding, and Multiscreen Navigation.  \n\nSection Timestamps:\nCreating a Project: 3:46\nStateful Widget: 5:22\nReactive State Changes: 12:16\nNetworking and Installing http Package: 14:58\nJSON Decoding: 20:51\nListView Builder: 25:00\nFile Refactoring: 34:06\nNavigation Page Routes: 41:16\n\nPodcasts Course\nhttps://www.letsbuildthatapp.com/course/Podcasts\n\nIntermediate Training Core Data\nhttps://www.letsbuildthatapp.com/course/intermediate-training-core-data\n\nInstagram Firebase Course\nhttps://www.letsbuildthatapp.com/course/instagram-firebase\n\nFacebook Group\nhttps://www.facebook.com/groups/1240636442694543/\n\nCompleted Source Code\nhttps://www.letsbuildthatapp.com/course_video?id=3082\n\nInstagram: https://www.instagram.com/buildthatapp/\nTwitter: https://twitter.com/buildthatapp", "thumbnails": {"default": {"url": "https://i.ytimg.com/vi/S59b-XFsyY8/default.jpg", "width": 120, "height": 90}, "medium": {"url": "https://i.ytimg.com/vi/S59b-XFsyY8/mqdefault.jpg", "width": 320, "height": 180}, "high": {"url": "https://i.ytimg.com/vi/S59b-XFsyY8/hqdefault.jpg", "width": 480, "height": 360}, "standard": {"url": "https://i.ytimg.com/vi/S59b-XFsyY8/sddefault.jpg", "width": 640, "height": 480}, "maxres": {"url": "https://i.ytimg.com/vi/S59b-XFsyY8/maxresdefault.jpg", "width": 1280, "height": 720}}, "channelTitle": "Lets Build That App", "tags": ["ios", "swift", "development", "tutorial", "learn", "xcode", "programming", "code", "flutter"], "categoryId": "27", "liveBroadcastContent": "none", "defaultLanguage": "en", "localized": {"title": "Complete Guide to Flutter: How to Build a Real World App", "description": "Flutter hit the scene a few months back and has caught the attention of quite a few developers.  In this guide, we'll go through all the necessary aspects of building out a Real World app that includes many features such as Reactive States, Networking, JSON Decoding, and Multiscreen Navigation.  \n\nSection Timestamps:\nCreating a Project: 3:46\nStateful Widget: 5:22\nReactive State Changes: 12:16\nNetworking and Installing http Package: 14:58\nJSON Decoding: 20:51\nListView Builder: 25:00\nFile Refactoring: 34:06\nNavigation Page Routes: 41:16\n\nPodcasts Course\nhttps://www.letsbuildthatapp.com/course/Podcasts\n\nIntermediate Training Core Data\nhttps://www.letsbuildthatapp.com/course/intermediate-training-core-data\n\nInstagram Firebase Course\nhttps://www.letsbuildthatapp.com/course/instagram-firebase\n\nFacebook Group\nhttps://www.facebook.com/groups/1240636442694543/\n\nCompleted Source Code\nhttps://www.letsbuildthatapp.com/course_video?id=3082\n\nInstagram: https://www.instagram.com/buildthatapp/\nTwitter: https://twitter.com/buildthatapp"}, "defaultAudioLanguage": "en"}, "contentDetails": {"duration": "PT46M24S", "dimension": "2d", "definition": "hd", "caption": "false", "licensedContent": true, "contentRating": {}, "projection": "rectangular"}, "statistics": {"viewCount": "96605", "likeCount": "2395", "dislikeCount": "52", "favoriteCount": "0", "commentCount": "301"}, "topicDetails": {"relevantTopicIds": ["/m/01k8wb", "/m/01k8wb"], "topicCategories": ["https://en.wikipedia.org/wiki/Knowledge"]}, "has_face": true, "detection_confidence": 0.9999327659606934}