{"kind": "youtube#video", "etag": "0mtXJXK6JRNdp_7EWsSvKfYkjyw", "id": "Vb5PvystQP0", "snippet": {"publishedAt": "2020-05-17T09:17:49Z", "channelId": "UC1fLEeYICmo3O9cUsqIi7HA", "title": "If Programming Was A Reality Show", "description": "Subscribe to Kevin's Channel! - https://youtube.com/kevinnaughtonjr\n\nPatreon - https://www.patreon.com/nick_white?al...\nMerch - https://teespring.com/stores/brain-juice\n\n___\nDiscord - https://discord.gg/2f2Tgy3\nTwitch - https://www.twitch.tv/matrixman\nTwitter - https://twitter.com/nicholaswwhite\nInstagram - https://instagram.com/nickwwhite\nLinkedIn - https://bit.ly/37AEo5j\nGithub - https://github.com/white105\n\nBecome a member of the channel! https://www.youtube.com/channel/UC1fLEeYICmo3O9cUsqIi7HA/join\n\n#Programming #RealityTV", "thumbnails": {"default": {"url": "https://i.ytimg.com/vi/Vb5PvystQP0/default.jpg", "width": 120, "height": 90}, "medium": {"url": "https://i.ytimg.com/vi/Vb5PvystQP0/mqdefault.jpg", "width": 320, "height": 180}, "high": {"url": "https://i.ytimg.com/vi/Vb5PvystQP0/hqdefault.jpg", "width": 480, "height": 360}, "standard": {"url": "https://i.ytimg.com/vi/Vb5PvystQP0/sddefault.jpg", "width": 640, "height": 480}, "maxres": {"url": "https://i.ytimg.com/vi/Vb5PvystQP0/maxresdefault.jpg", "width": 1280, "height": 720}}, "channelTitle": "Nick White", "tags": ["if programming were a reality show", "reality tv", "reality show", "dramatic developers", "developers", "developer", "nick white dramatic developers", "nick white", "kevin naughton jr", "coding", "programming", "education", "tech", "swe", "software engineering", "software development", "software engineer", "software developer", "web developer", "coder", "programmer", "computer science", "computer programming", "code", "program"], "categoryId": "28", "liveBroadcastContent": "none", "localized": {"title": "If Programming Was A Reality Show", "description": "Subscribe to Kevin's Channel! - https://youtube.com/kevinnaughtonjr\n\nPatreon - https://www.patreon.com/nick_white?al...\nMerch - https://teespring.com/stores/brain-juice\n\n___\nDiscord - https://discord.gg/2f2Tgy3\nTwitch - https://www.twitch.tv/matrixman\nTwitter - https://twitter.com/nicholaswwhite\nInstagram - https://instagram.com/nickwwhite\nLinkedIn - https://bit.ly/37AEo5j\nGithub - https://github.com/white105\n\nBecome a member of the channel! https://www.youtube.com/channel/UC1fLEeYICmo3O9cUsqIi7HA/join\n\n#Programming #RealityTV"}}, "contentDetails": {"duration": "PT3M11S", "dimension": "2d", "definition": "hd", "caption": "false", "licensedContent": false, "contentRating": {}, "projection": "rectangular"}, "statistics": {"viewCount": "14332", "likeCount": "934", "dislikeCount": "27", "favoriteCount": "0", "commentCount": "92"}, "topicDetails": {"relevantTopicIds": ["/m/019_rr", "/m/0kt51", "/m/019_rr", "/m/0kt51"], "topicCategories": ["https://en.wikipedia.org/wiki/Health", "https://en.wikipedia.org/wiki/Lifestyle_(sociology)"]}, "has_face": true, "detection_confidence": 0.9998815059661865}